[
  {
    "value": 10.590071,
    "date": "2022-10-26T00:00:00.000Z"
  },
  {
    "value": 9.850071,
    "date": "2022-10-26T01:00:00.000Z"
  },
  {
    "value": 9.350071,
    "date": "2022-10-26T02:00:00.000Z"
  },
  {
    "value": 8.620071,
    "date": "2022-10-26T03:00:00.000Z"
  },
  {
    "value": 7.7700715,
    "date": "2022-10-26T04:00:00.000Z"
  },
  {
    "value": 6.8800716,
    "date": "2022-10-26T05:00:00.000Z"
  },
  {
    "value": 7.1700716,
    "date": "2022-10-26T06:00:00.000Z"
  },
  {
    "value": 8.930071,
    "date": "2022-10-26T07:00:00.000Z"
  },
  {
    "value": 12.470071,
    "date": "2022-10-26T08:00:00.000Z"
  },
  {
    "value": 14.700071,
    "date": "2022-10-26T09:00:00.000Z"
  },
  {
    "value": 16.160072,
    "date": "2022-10-26T10:00:00.000Z"
  },
  {
    "value": 17.690071,
    "date": "2022-10-26T11:00:00.000Z"
  },
  {
    "value": 18.390072,
    "date": "2022-10-26T12:00:00.000Z"
  },
  {
    "value": 18.180073,
    "date": "2022-10-26T13:00:00.000Z"
  },
  {
    "value": 18.780071,
    "date": "2022-10-26T14:00:00.000Z"
  },
  {
    "value": 18.330072,
    "date": "2022-10-26T15:00:00.000Z"
  },
  {
    "value": 17.580072,
    "date": "2022-10-26T16:00:00.000Z"
  },
  {
    "value": 17.280071,
    "date": "2022-10-26T17:00:00.000Z"
  },
  {
    "value": 16.900072,
    "date": "2022-10-26T18:00:00.000Z"
  },
  {
    "value": 16.190071,
    "date": "2022-10-26T19:00:00.000Z"
  },
  {
    "value": 15.520071,
    "date": "2022-10-26T20:00:00.000Z"
  },
  {
    "value": 14.670071,
    "date": "2022-10-26T21:00:00.000Z"
  },
  {
    "value": 15.320071,
    "date": "2022-10-26T22:00:00.000Z"
  },
  {
    "value": 14.580071,
    "date": "2022-10-26T23:00:00.000Z"
  }
]
