[
  {
    "value": 8.890071,
    "date": "2022-10-15T00:00:00.000Z"
  },
  {
    "value": 9.260071,
    "date": "2022-10-15T01:00:00.000Z"
  },
  {
    "value": 9.300071,
    "date": "2022-10-15T02:00:00.000Z"
  },
  {
    "value": 9.420071,
    "date": "2022-10-15T03:00:00.000Z"
  },
  {
    "value": 9.800071,
    "date": "2022-10-15T04:00:00.000Z"
  },
  {
    "value": 10.100071,
    "date": "2022-10-15T05:00:00.000Z"
  },
  {
    "value": 10.690071,
    "date": "2022-10-15T06:00:00.000Z"
  },
  {
    "value": 12.210071,
    "date": "2022-10-15T07:00:00.000Z"
  },
  {
    "value": 15.500071,
    "date": "2022-10-15T08:00:00.000Z"
  },
  {
    "value": 16.760073,
    "date": "2022-10-15T09:00:00.000Z"
  },
  {
    "value": 18.230072,
    "date": "2022-10-15T10:00:00.000Z"
  },
  {
    "value": 18.370071,
    "date": "2022-10-15T11:00:00.000Z"
  },
  {
    "value": 15.790071,
    "date": "2022-10-15T12:00:00.000Z"
  },
  {
    "value": 14.240071,
    "date": "2022-10-15T13:00:00.000Z"
  },
  {
    "value": 14.150071,
    "date": "2022-10-15T14:00:00.000Z"
  },
  {
    "value": 13.150071,
    "date": "2022-10-15T15:00:00.000Z"
  },
  {
    "value": 12.410071,
    "date": "2022-10-15T16:00:00.000Z"
  },
  {
    "value": 12.530071,
    "date": "2022-10-15T17:00:00.000Z"
  },
  {
    "value": 12.560071,
    "date": "2022-10-15T18:00:00.000Z"
  },
  {
    "value": 12.680071,
    "date": "2022-10-15T19:00:00.000Z"
  },
  {
    "value": 12.900071,
    "date": "2022-10-15T20:00:00.000Z"
  },
  {
    "value": 12.940071,
    "date": "2022-10-15T21:00:00.000Z"
  },
  {
    "value": 11.580071,
    "date": "2022-10-15T22:00:00.000Z"
  },
  {
    "value": 11.270071,
    "date": "2022-10-15T23:00:00.000Z"
  }
]
