[
  {
    "value": 9.360071,
    "date": "2022-10-23T00:00:00.000Z"
  },
  {
    "value": 9.380071,
    "date": "2022-10-23T01:00:00.000Z"
  },
  {
    "value": 9.530071,
    "date": "2022-10-23T02:00:00.000Z"
  },
  {
    "value": 8.940071,
    "date": "2022-10-23T03:00:00.000Z"
  },
  {
    "value": 8.000072,
    "date": "2022-10-23T04:00:00.000Z"
  },
  {
    "value": 7.4400716,
    "date": "2022-10-23T05:00:00.000Z"
  },
  {
    "value": 7.2400713,
    "date": "2022-10-23T06:00:00.000Z"
  },
  {
    "value": 9.450071,
    "date": "2022-10-23T07:00:00.000Z"
  },
  {
    "value": 12.180071,
    "date": "2022-10-23T08:00:00.000Z"
  },
  {
    "value": 15.420071,
    "date": "2022-10-23T09:00:00.000Z"
  },
  {
    "value": 17.640072,
    "date": "2022-10-23T10:00:00.000Z"
  },
  {
    "value": 19.300072,
    "date": "2022-10-23T11:00:00.000Z"
  },
  {
    "value": 20.130072,
    "date": "2022-10-23T12:00:00.000Z"
  },
  {
    "value": 19.960072,
    "date": "2022-10-23T13:00:00.000Z"
  },
  {
    "value": 19.780071,
    "date": "2022-10-23T14:00:00.000Z"
  },
  {
    "value": 18.710072,
    "date": "2022-10-23T15:00:00.000Z"
  },
  {
    "value": 15.340071,
    "date": "2022-10-23T16:00:00.000Z"
  },
  {
    "value": 14.100071,
    "date": "2022-10-23T17:00:00.000Z"
  },
  {
    "value": 12.940071,
    "date": "2022-10-23T18:00:00.000Z"
  },
  {
    "value": 12.310071,
    "date": "2022-10-23T19:00:00.000Z"
  },
  {
    "value": 12.020071,
    "date": "2022-10-23T20:00:00.000Z"
  },
  {
    "value": 11.880071,
    "date": "2022-10-23T21:00:00.000Z"
  },
  {
    "value": 11.690071,
    "date": "2022-10-23T22:00:00.000Z"
  },
  {
    "value": 11.770071,
    "date": "2022-10-23T23:00:00.000Z"
  }
]
