[
  {
    "value": 14.190071,
    "date": "2022-05-12T00:00:00.000Z"
  },
  {
    "value": 13.980071,
    "date": "2022-05-12T01:00:00.000Z"
  },
  {
    "value": 14.390071,
    "date": "2022-05-12T02:00:00.000Z"
  },
  {
    "value": 13.520071,
    "date": "2022-05-12T03:00:00.000Z"
  },
  {
    "value": 14.330071,
    "date": "2022-05-12T04:00:00.000Z"
  },
  {
    "value": 17.950071,
    "date": "2022-05-12T05:00:00.000Z"
  },
  {
    "value": 21.790071,
    "date": "2022-05-12T06:00:00.000Z"
  },
  {
    "value": 25.010073,
    "date": "2022-05-12T07:00:00.000Z"
  },
  {
    "value": 27.300072,
    "date": "2022-05-12T08:00:00.000Z"
  },
  {
    "value": 28.640072,
    "date": "2022-05-12T09:00:00.000Z"
  },
  {
    "value": 29.280071,
    "date": "2022-05-12T10:00:00.000Z"
  },
  {
    "value": 28.840073,
    "date": "2022-05-12T11:00:00.000Z"
  },
  {
    "value": 28.810072,
    "date": "2022-05-12T12:00:00.000Z"
  },
  {
    "value": 27.830072,
    "date": "2022-05-12T13:00:00.000Z"
  },
  {
    "value": 27.340073,
    "date": "2022-05-12T14:00:00.000Z"
  },
  {
    "value": 27.050072,
    "date": "2022-05-12T15:00:00.000Z"
  },
  {
    "value": 26.440071,
    "date": "2022-05-12T16:00:00.000Z"
  },
  {
    "value": 26.010073,
    "date": "2022-05-12T17:00:00.000Z"
  },
  {
    "value": 24.350073,
    "date": "2022-05-12T18:00:00.000Z"
  },
  {
    "value": 20.380072,
    "date": "2022-05-12T19:00:00.000Z"
  },
  {
    "value": 18.700071,
    "date": "2022-05-12T20:00:00.000Z"
  },
  {
    "value": 17.700071,
    "date": "2022-05-12T21:00:00.000Z"
  },
  {
    "value": 17.060072,
    "date": "2022-05-12T22:00:00.000Z"
  },
  {
    "value": 17.260073,
    "date": "2022-05-12T23:00:00.000Z"
  }
]
