[
  {
    "value": 14.370071,
    "date": "2022-08-10T00:00:00.000Z"
  },
  {
    "value": 13.250071,
    "date": "2022-08-10T01:00:00.000Z"
  },
  {
    "value": 12.420071,
    "date": "2022-08-10T02:00:00.000Z"
  },
  {
    "value": 11.740071,
    "date": "2022-08-10T03:00:00.000Z"
  },
  {
    "value": 11.840071,
    "date": "2022-08-10T04:00:00.000Z"
  },
  {
    "value": 15.400071,
    "date": "2022-08-10T05:00:00.000Z"
  },
  {
    "value": 19.390072,
    "date": "2022-08-10T06:00:00.000Z"
  },
  {
    "value": 22.940071,
    "date": "2022-08-10T07:00:00.000Z"
  },
  {
    "value": 24.670073,
    "date": "2022-08-10T08:00:00.000Z"
  },
  {
    "value": 25.780071,
    "date": "2022-08-10T09:00:00.000Z"
  },
  {
    "value": 26.680073,
    "date": "2022-08-10T10:00:00.000Z"
  },
  {
    "value": 27.430073,
    "date": "2022-08-10T11:00:00.000Z"
  },
  {
    "value": 27.900072,
    "date": "2022-08-10T12:00:00.000Z"
  },
  {
    "value": 28.150072,
    "date": "2022-08-10T13:00:00.000Z"
  },
  {
    "value": 28.230072,
    "date": "2022-08-10T14:00:00.000Z"
  },
  {
    "value": 27.910072,
    "date": "2022-08-10T15:00:00.000Z"
  },
  {
    "value": 27.280071,
    "date": "2022-08-10T16:00:00.000Z"
  },
  {
    "value": 26.170073,
    "date": "2022-08-10T17:00:00.000Z"
  },
  {
    "value": 23.190071,
    "date": "2022-08-10T18:00:00.000Z"
  },
  {
    "value": 19.840073,
    "date": "2022-08-10T19:00:00.000Z"
  },
  {
    "value": 18.210072,
    "date": "2022-08-10T20:00:00.000Z"
  },
  {
    "value": 16.850073,
    "date": "2022-08-10T21:00:00.000Z"
  },
  {
    "value": 15.660071,
    "date": "2022-08-10T22:00:00.000Z"
  },
  {
    "value": 14.690071,
    "date": "2022-08-10T23:00:00.000Z"
  }
]
