[
  {
    "value": 19.560072,
    "date": "2022-08-05T00:00:00.000Z"
  },
  {
    "value": 18.560072,
    "date": "2022-08-05T01:00:00.000Z"
  },
  {
    "value": 17.860071,
    "date": "2022-08-05T02:00:00.000Z"
  },
  {
    "value": 17.900072,
    "date": "2022-08-05T03:00:00.000Z"
  },
  {
    "value": 18.750072,
    "date": "2022-08-05T04:00:00.000Z"
  },
  {
    "value": 21.920073,
    "date": "2022-08-05T05:00:00.000Z"
  },
  {
    "value": 24.930073,
    "date": "2022-08-05T06:00:00.000Z"
  },
  {
    "value": 28.740072,
    "date": "2022-08-05T07:00:00.000Z"
  },
  {
    "value": 31.600073,
    "date": "2022-08-05T08:00:00.000Z"
  },
  {
    "value": 33.52007,
    "date": "2022-08-05T09:00:00.000Z"
  },
  {
    "value": 34.89007,
    "date": "2022-08-05T10:00:00.000Z"
  },
  {
    "value": 36.21007,
    "date": "2022-08-05T11:00:00.000Z"
  },
  {
    "value": 37.03007,
    "date": "2022-08-05T12:00:00.000Z"
  },
  {
    "value": 37.43007,
    "date": "2022-08-05T13:00:00.000Z"
  },
  {
    "value": 37.62007,
    "date": "2022-08-05T14:00:00.000Z"
  },
  {
    "value": 37.38007,
    "date": "2022-08-05T15:00:00.000Z"
  },
  {
    "value": 36.86007,
    "date": "2022-08-05T16:00:00.000Z"
  },
  {
    "value": 36.01007,
    "date": "2022-08-05T17:00:00.000Z"
  },
  {
    "value": 33.53007,
    "date": "2022-08-05T18:00:00.000Z"
  },
  {
    "value": 31.460072,
    "date": "2022-08-05T19:00:00.000Z"
  },
  {
    "value": 30.220072,
    "date": "2022-08-05T20:00:00.000Z"
  },
  {
    "value": 29.050072,
    "date": "2022-08-05T21:00:00.000Z"
  },
  {
    "value": 28.100073,
    "date": "2022-08-05T22:00:00.000Z"
  },
  {
    "value": 26.740072,
    "date": "2022-08-05T23:00:00.000Z"
  }
]
